Metadata-Version: 2.1
Name: pksycopg2
Version: 2.9.0
Summary: pksycopg2 - patched ksycopg2
License: GNU Library or Lesser General Public License (LGPL) (LGPL with exceptions)
Requires-Python: >=3.10
